{
  "swagger": "2.0",
  "info": {
    "title": "room.proto",
    "version": "version not set"
  },
  "tags": [
    {
      "name": "RoomService"
    }
  ],
  "consumes": [
    "application/json"
  ],
  "produces": [
    "application/json"
  ],
  "paths": {
    "/api/v1/room/create": {
      "post": {
        "operationId": "RoomService_CreateRoom",
        "responses": {
          "200": {
            "description": "A successful response.",
            "schema": {
              "$ref": "#/definitions/v1StandardResponse"
            }
          },
          "default": {
            "description": "An unexpected error response.",
            "schema": {
              "$ref": "#/definitions/rpcStatus"
            }
          }
        },
        "parameters": [
          {
            "name": "body",
            "in": "body",
            "required": true,
            "schema": {
              "$ref": "#/definitions/v1CreateRoomRequest"
            }
          }
        ],
        "tags": [
          "RoomService"
        ]
      }
    },
    "/api/v1/room/delete/{roomId}": {
      "delete": {
        "operationId": "RoomService_DeleteRoom",
        "responses": {
          "200": {
            "description": "A successful response.",
            "schema": {
              "$ref": "#/definitions/v1StandardResponse"
            }
          },
          "default": {
            "description": "An unexpected error response.",
            "schema": {
              "$ref": "#/definitions/rpcStatus"
            }
          }
        },
        "parameters": [
          {
            "name": "roomId",
            "in": "path",
            "required": true,
            "type": "string"
          }
        ],
        "tags": [
          "RoomService"
        ]
      }
    },
    "/api/v1/room/{roomId}": {
      "get": {
        "summary": "投稿操作",
        "operationId": "RoomService_GetRoom",
        "responses": {
          "200": {
            "description": "A successful response.",
            "schema": {
              "$ref": "#/definitions/v1GetRoomResponse"
            }
          },
          "default": {
            "description": "An unexpected error response.",
            "schema": {
              "$ref": "#/definitions/rpcStatus"
            }
          }
        },
        "parameters": [
          {
            "name": "roomId",
            "in": "path",
            "required": true,
            "type": "string"
          }
        ],
        "tags": [
          "RoomService"
        ]
      }
    }
  },
  "definitions": {
    "protobufAny": {
      "type": "object",
      "properties": {
        "@type": {
          "type": "string"
        }
      },
      "additionalProperties": {}
    },
    "rpcStatus": {
      "type": "object",
      "properties": {
        "code": {
          "type": "integer",
          "format": "int32"
        },
        "message": {
          "type": "string"
        },
        "details": {
          "type": "array",
          "items": {
            "type": "object",
            "$ref": "#/definitions/protobufAny"
          }
        }
      }
    },
    "v1CreateRoomRequest": {
      "type": "object",
      "properties": {
        "userName": {
          "type": "string"
        },
        "userId": {
          "type": "string"
        }
      }
    },
    "v1GetRoomResponse": {
      "type": "object",
      "properties": {
        "room": {
          "$ref": "#/definitions/v1Room"
        }
      }
    },
    "v1Room": {
      "type": "object",
      "properties": {
        "roomId": {
          "type": "string"
        },
        "users": {
          "type": "array",
          "items": {
            "type": "object",
            "$ref": "#/definitions/v1User"
          }
        }
      }
    },
    "v1StandardResponse": {
      "type": "object",
      "properties": {
        "success": {
          "type": "boolean"
        },
        "message": {
          "type": "string"
        }
      }
    },
    "v1User": {
      "type": "object",
      "properties": {
        "userName": {
          "type": "string"
        },
        "userId": {
          "type": "string"
        },
        "userImage": {
          "type": "string"
        }
      }
    }
  }
}
